egehelperforschool2/main.py
egehelperforschool2-1.0.dist-info/METADATA
egehelperforschool2-1.0.dist-info/WHEEL
egehelperforschool2-1.0.dist-info/top_level.txt
egehelperforschool2-1.0.dist-info/RECORD
